turbofloat/__init__.py
turbofloat/c_wrapper.py
turbofloat-4.4.4.1.dist-info/LICENSE
turbofloat-4.4.4.1.dist-info/METADATA
turbofloat-4.4.4.1.dist-info/WHEEL
turbofloat-4.4.4.1.dist-info/top_level.txt
turbofloat-4.4.4.1.dist-info/RECORD
