Metadata-Version: 2.1
Name: turbofloat
Version: 4.4.4.1
Summary: Python integration for the LimeLM TurboFloat library. This lets you add floating licensing (a.k.a. concurrent licensing) to your Python app.
Home-page: https://wyday.com/limelm/help/using-turbofloat-with-python/
Author: wyDay, LLC
Author-email: support@wyday.com
Maintainer: wyDay, LLC
Maintainer-email: support@wyday.com
License: UNKNOWN
Download-URL: https://github.com/wyday/python-turbofloat
Platform: UNKNOWN
Classifier: Development Status :: 5 - Production/Stable
Classifier: Intended Audience :: Developers
Classifier: License :: OSI Approved :: MIT License
Classifier: Topic :: Software Development :: Libraries :: Python Modules
Classifier: Programming Language :: Python
Classifier: Programming Language :: Python :: 2
Classifier: Programming Language :: Python :: 3
